keet/__init__.py
keet/main.py
keet-0.0.3.dist-info/licenses/LICENSE
keet-0.0.3.dist-info/METADATA
keet-0.0.3.dist-info/WHEEL
keet-0.0.3.dist-info/top_level.txt
keet-0.0.3.dist-info/RECORD
