Metadata-Version: 2.4
Name: keet
Version: 0.0.3
Summary: Simple python library for creating your keet bots
Home-page: https://github.com/lmemq/keetbot
Author: lime
Classifier: Programming Language :: Python :: 3
Classifier: License :: OSI Approved :: MIT License
Classifier: Operating System :: OS Independent
Requires-Python: >=3.9
License-File: LICENSE
Dynamic: license-file
